README.md
setup.py
chain33/__init__.py
chain33.egg-info/PKG-INFO
chain33.egg-info/SOURCES.txt
chain33.egg-info/dependency_links.txt
chain33.egg-info/requires.txt
chain33.egg-info/top_level.txt
chain33/crypto/__init__.py
chain33/crypto/account.py
chain33/crypto/address.py
chain33/crypto/aes.py
chain33/crypto/pre.py
chain33/crypto/signer.py
chain33/crypto/ed25519/__init__.py
chain33/crypto/ed25519/ed25519Signer.py
chain33/crypto/gm/__init__.py
chain33/crypto/gm/sm2.py
chain33/crypto/gm/sm3.py
chain33/crypto/gm/sm4.py
chain33/dapp/__init__.py
chain33/dapp/coins.py
chain33/dapp/manage.py
chain33/dapp/storage.py
chain33/dapp/token.py
chain33/dapp/transaction.py
chain33/protobuf/__init__.py
chain33/protobuf/manage_pb2.py
chain33/protobuf/storage_pb2.py
chain33/protobuf/tx_pb2.py
chain33/rpc/__init__.py
chain33/rpc/jsonclient.py
chain33/rpc/types.py