Metadata-Version: 1.0
Name: chain33
Version: 0.2
Summary: Pure Python SDK for Chain33
Home-page: https://github.com/33cn/chain33-sdk-python
Author: harrylee
Author-email: 18761806026@163.com
License: UNKNOWN
Keywords: blockchain,chain33,sdk
Platform: UNKNOWN
